cdktf_cdktf_provider_vault/__init__.py
cdktf_cdktf_provider_vault/py.typed
cdktf_cdktf_provider_vault/_jsii/__init__.py
cdktf_cdktf_provider_vault/_jsii/provider-vault@15.4.0.jsii.tgz
cdktf_cdktf_provider_vault/ad_secret_backend/__init__.py
cdktf_cdktf_provider_vault/ad_secret_library/__init__.py
cdktf_cdktf_provider_vault/ad_secret_role/__init__.py
cdktf_cdktf_provider_vault/alicloud_auth_backend_role/__init__.py
cdktf_cdktf_provider_vault/approle_auth_backend_login/__init__.py
cdktf_cdktf_provider_vault/approle_auth_backend_role/__init__.py
cdktf_cdktf_provider_vault/approle_auth_backend_role_secret_id/__init__.py
cdktf_cdktf_provider_vault/audit/__init__.py
cdktf_cdktf_provider_vault/audit_request_header/__init__.py
cdktf_cdktf_provider_vault/auth_backend/__init__.py
cdktf_cdktf_provider_vault/aws_auth_backend_cert/__init__.py
cdktf_cdktf_provider_vault/aws_auth_backend_client/__init__.py
cdktf_cdktf_provider_vault/aws_auth_backend_config_identity/__init__.py
cdktf_cdktf_provider_vault/aws_auth_backend_identity_whitelist/__init__.py
cdktf_cdktf_provider_vault/aws_auth_backend_login/__init__.py
cdktf_cdktf_provider_vault/aws_auth_backend_role/__init__.py
cdktf_cdktf_provider_vault/aws_auth_backend_role_tag/__init__.py
cdktf_cdktf_provider_vault/aws_auth_backend_roletag_blacklist/__init__.py
cdktf_cdktf_provider_vault/aws_auth_backend_sts_role/__init__.py
cdktf_cdktf_provider_vault/aws_secret_backend/__init__.py
cdktf_cdktf_provider_vault/aws_secret_backend_role/__init__.py
cdktf_cdktf_provider_vault/aws_secret_backend_static_role/__init__.py
cdktf_cdktf_provider_vault/azure_auth_backend_config/__init__.py
cdktf_cdktf_provider_vault/azure_auth_backend_role/__init__.py
cdktf_cdktf_provider_vault/azure_secret_backend/__init__.py
cdktf_cdktf_provider_vault/azure_secret_backend_role/__init__.py
cdktf_cdktf_provider_vault/azure_secret_backend_static_role/__init__.py
cdktf_cdktf_provider_vault/cert_auth_backend_role/__init__.py
cdktf_cdktf_provider_vault-15.4.0.dist-info/LICENSE
cdktf_cdktf_provider_vault-15.4.0.dist-info/METADATA
cdktf_cdktf_provider_vault-15.4.0.dist-info/WHEEL
cdktf_cdktf_provider_vault-15.4.0.dist-info/top_level.txt
cdktf_cdktf_provider_vault-15.4.0.dist-info/RECORD
